<mvc:View xmlns:uxap="sap.uxap" controllerName="practiceapp.practicej.controller.Tiles"
    xmlns:mvc="sap.ui.core.mvc" displayBlock="true"
    xmlns="sap.m"
    xmlns:l="sap.ui.layout"
    xmlns:cust="practiceapp.practicej.control">

    <Page >
        <content>
            <GenericTile class="sapUiTinyMarginBegin sapUiTinyMarginTop tileLayout" header="Flights app"  press="onPressFlights"
            frameType="OneByHalf" subheader="Flights"  > </GenericTile>

             <GenericTile class="sapUiTinyMarginBegin sapUiTinyMarginTop tileLayout" header="Smart Table"  press="onPressSmarttable"
            frameType="OneByHalf" subheader="Smart Table"  > </GenericTile>

    <GenericTile class="sapUiTinyMarginBegin sapUiTinyMarginTop tileLayout" header="Charts"  press="onPressCharts"
                frameType="OneByHalf" subheader="Smart Table"  > </GenericTile>



        </content>
        </Page>


</mvc:View>